car_parking_system.v
// car_parking_system.v
module car_parking_system(
    input wire [7:0] sensors,
    output reg [7:0] parking_spaces
);

// Initialize parking_spaces
initial begin
    parking_spaces = 8'b00000000;
end

genvar i;
generate
    for (i = 0; i < 8; i = i + 1) begin : parking_space_logic
        always @(*) begin  // Changed to always @(*) for combinational logic
            // Sensor logic to update parking space status
            parking_spaces[i] = sensors[i];  // Direct assignment instead of toggle
        end
    end
endgenerate
endmodule

car_parking_system_tb.v
// car_parking_system_tb.v
`timescale 1ns/1ns  // Set the timescale for simulation
module tb_car_parking_system;
  // Inputs
  reg sensor1;
  reg sensor2;
  reg sensor3;
  reg sensor4;
  reg sensor5;
  reg sensor6;
  reg sensor7;
  reg sensor8;
  // Outputs
  wire [7:0] parking_spaces;
  
  integer i;  // Loop variable for displaying free slots
  
  // Instantiate the module under test
  car_parking_system uut (
    .sensors({sensor8, sensor7, sensor6, sensor5, sensor4, sensor3, sensor2, sensor1}),  // Changed order
    .parking_spaces(parking_spaces)
  );
  
  // File for VCD (Value Change Dump) output
  initial begin
    $dumpfile("car_parking_system_tb.vcd");
    $dumpvars(0, tb_car_parking_system);
  end
  
  // Initial block for stimulus generation
  initial begin
    // Test case 1: No cars, all spaces should be vacant
    sensor1 = 0;
    sensor2 = 0;
    sensor3 = 0;
    sensor4 = 0;
    sensor5 = 0;
    sensor6 = 0;
    sensor7 = 0;
    sensor8 = 0;
    #10;  // Wait for 10 time units
    $display("\n--- Parking Status at time %0t ---", $time);
    $display("Occupied Spaces (binary): %b", parking_spaces);
    $display("Free Parking Slots:");
    for (i = 7; i >= 0; i = i - 1) begin  // Changed loop direction
      if (parking_spaces[i] == 0) begin
        $display("  Slot %0d is FREE", 8 - i);  // Changed slot numbering
      end
    end
    $display("-----------------------------------\n");
    
    // Test case 2: Car in space 1, other spaces vacant
    sensor1 = 1;
    sensor2 = 0;
    sensor3 = 0;
    sensor4 = 0;
    sensor5 = 0;
    sensor6 = 0;
    sensor7 = 0;
    sensor8 = 0;
    #10;
    $display("\n--- Parking Status at time %0t ---", $time);
    $display("Occupied Spaces (binary): %b", parking_spaces);
    $display("Free Parking Slots:");
    for (i = 7; i >= 0; i = i - 1) begin
      if (parking_spaces[i] == 0) begin
        $display("  Slot %0d is FREE", 8 - i);
      end
    end
    $display("-----------------------------------\n");
    
    // Test case 3: Car in space 2, other spaces vacant
    sensor1 = 0;
    sensor2 = 1;
    sensor3 = 0;
    sensor4 = 0;
    sensor5 = 0;
    sensor6 = 0;
    sensor7 = 0;
    sensor8 = 0;
    #10;
    $display("\n--- Parking Status at time %0t ---", $time);
    $display("Occupied Spaces (binary): %b", parking_spaces);
    $display("Free Parking Slots:");
    for (i = 7; i >= 0; i = i - 1) begin
      if (parking_spaces[i] == 0) begin
        $display("  Slot %0d is FREE", 8 - i);
      end
    end
    $display("-----------------------------------\n");
    
    // Test case 4: Cars in spaces 1 and 2, other spaces vacant
    sensor1 = 1;
    sensor2 = 1;
    sensor3 = 0;
    sensor4 = 0;
    sensor5 = 0;
    sensor6 = 0;
    sensor7 = 0;
    sensor8 = 0;
    #10;
    $display("\n--- Parking Status at time %0t ---", $time);
    $display("Occupied Spaces (binary): %b", parking_spaces);
    $display("Free Parking Slots:");
    for (i = 7; i >= 0; i = i - 1) begin
      if (parking_spaces[i] == 0) begin
        $display("  Slot %0d is FREE", 8 - i);
      end
    end
    $display("-----------------------------------\n");
    
    // Test case 5: Cars in spaces 7 and 8, other spaces vacant
    sensor1 = 0;
    sensor2 = 0;
    sensor3 = 0;
    sensor4 = 0;
    sensor5 = 0;
    sensor6 = 0;
    sensor7 = 1;
    sensor8 = 1;
    #10;
    $display("\n--- Parking Status at time %0t ---", $time);
    $display("Occupied Spaces (binary): %b", parking_spaces);
    $display("Free Parking Slots:");
    for (i = 7; i >= 0; i = i - 1) begin
      if (parking_spaces[i] == 0) begin
        $display("  Slot %0d is FREE", 8 - i);
      end
    end
    $display("-----------------------------------\n");
    
    // Test case 6: Cars in spaces 1,3, 5 and 7, other spaces vacant
    sensor1 = 1;
    sensor2 = 0;
    sensor3 = 1;
    sensor4 = 0;
    sensor5 = 1;
    sensor6 = 0;
    sensor7 = 1;
    sensor8 = 0;
    #10;
    $display("\n--- Parking Status at time %0t ---", $time);
    $display("Occupied Spaces (binary): %b", parking_spaces);
    $display("Free Parking Slots:");
    for (i = 7; i >= 0; i = i - 1) begin
      if (parking_spaces[i] == 0) begin
        $display("  Slot %0d is FREE", 8 - i);
      end
    end
    $display("-----------------------------------\n");
    
    // Test case 7: Cars in spaces 2, 4, 6 and 8, other spaces vacant
    sensor1 = 0;
    sensor2 = 1;
    sensor3 = 0;
    sensor4 = 1;
    sensor5 = 0;
    sensor6 = 1;
    sensor7 = 0;
    sensor8 = 1;
    #10;
    $display("\n--- Parking Status at time %0t ---", $time);
    $display("Occupied Spaces (binary): %b", parking_spaces);
    $display("Free Parking Slots:");
    for (i = 7; i >= 0; i = i - 1) begin
      if (parking_spaces[i] == 0) begin
        $display("  Slot %0d is FREE", 8 - i);
      end
    end
    $display("-----------------------------------\n");
    
    // Test case 8: Cars in all spaces
    sensor1 = 1;
    sensor2 = 1;
    sensor3 = 1;
    sensor4 = 1;
    sensor5 = 1;
    sensor6 = 1;
    sensor7 = 1;
    sensor8 = 1;
    #10;
    $display("\n--- Parking Status at time %0t ---", $time);
    $display("Occupied Spaces (binary): %b", parking_spaces);
    $display("Free Parking Slots:");
    for (i = 7; i >= 0; i = i - 1) begin
      if (parking_spaces[i] == 0) begin
        $display("  Slot %0d is FREE", 8 - i);
      end
    end
    $display("-----------------------------------\n");
    
    $stop;  // Stop simulation
  end
endmodule

car_parking_system_tb.vcd
$date
	Wed Nov 12 14:14:23 2025
$end
$version
	Icarus Verilog
$end
$timescale
	1ns
$end
$scope module tb_car_parking_system $end
$var wire 8 ! parking_spaces [7:0] $end
$var reg 1 " sensor1 $end
$var reg 1 # sensor2 $end
$var reg 1 $ sensor3 $end
$var reg 1 % sensor4 $end
$var reg 1 & sensor5 $end
$var reg 1 ' sensor6 $end
$var reg 1 ( sensor7 $end
$var reg 1 ) sensor8 $end
$var integer 32 * i [31:0] $end
$scope module uut $end
$var wire 8 + sensors [7:0] $end
$var reg 8 , parking_spaces [7:0] $end
$scope begin parking_space_logic[0] $end
$var parameter 2 - i $end
$upscope $end
$scope begin parking_space_logic[1] $end
$var parameter 2 . i $end
$upscope $end
$scope begin parking_space_logic[2] $end
$var parameter 3 / i $end
$upscope $end
$scope begin parking_space_logic[3] $end
$var parameter 3 0 i $end
$upscope $end
$scope begin parking_space_logic[4] $end
$var parameter 4 1 i $end
$upscope $end
$scope begin parking_space_logic[5] $end
$var parameter 4 2 i $end
$upscope $end
$scope begin parking_space_logic[6] $end
$var parameter 4 3 i $end
$upscope $end
$scope begin parking_space_logic[7] $end
$var parameter 4 4 i $end
$upscope $end
$upscope $end
$upscope $end
$enddefinitions $end
$comment Show the parameter values. $end
$dumpall
b111 4
b110 3
b101 2
b100 1
b11 0
b10 /
b1 .
b0 -
$end
#0
$dumpvars
b0 ,
b0 +
bx *
0)
0(
0'
0&
0%
0$
0#
0"
b0 !
$end
#10
b1 !
b1 ,
b1 +
1"
b11111111111111111111111111111111 *
#20
b10 !
b10 ,
1#
b10 +
0"
b11111111111111111111111111111111 *
#30
b11 !
b11 ,
b11 +
1"
b11111111111111111111111111111111 *
#40
b11000000 !
b11000000 ,
1)
1(
0#
b11000000 +
0"
b11111111111111111111111111111111 *
#50
b1010101 !
b1010101 ,
0)
1&
1$
b1010101 +
1"
b11111111111111111111111111111111 *
#60
b10101010 !
b10101010 ,
1)
0(
1'
0&
1%
0$
1#
b10101010 +
0"
b11111111111111111111111111111111 *
#70
b11111111 !
b11111111 ,
1(
1&
1$
b11111111 +
1"
b11111111111111111111111111111111 *
